fleetfinder/__init__.py
fleetfinder/app_settings.py
fleetfinder/apps.py
fleetfinder/auth_hooks.py
fleetfinder/models.py
fleetfinder/providers.py
fleetfinder/tasks.py
fleetfinder/urls.py
fleetfinder/views.py
fleetfinder/handler/esi_handler.py
fleetfinder/locale/django.pot
fleetfinder/locale/cs_CZ/LC_MESSAGES/django.mo
fleetfinder/locale/cs_CZ/LC_MESSAGES/django.po
fleetfinder/locale/de/LC_MESSAGES/django.mo
fleetfinder/locale/de/LC_MESSAGES/django.po
fleetfinder/locale/es/LC_MESSAGES/django.mo
fleetfinder/locale/es/LC_MESSAGES/django.po
fleetfinder/locale/fr_FR/LC_MESSAGES/django.mo
fleetfinder/locale/fr_FR/LC_MESSAGES/django.po
fleetfinder/locale/it_IT/LC_MESSAGES/django.mo
fleetfinder/locale/it_IT/LC_MESSAGES/django.po
fleetfinder/locale/ja/LC_MESSAGES/django.mo
fleetfinder/locale/ja/LC_MESSAGES/django.po
fleetfinder/locale/ko_KR/LC_MESSAGES/django.mo
fleetfinder/locale/ko_KR/LC_MESSAGES/django.po
fleetfinder/locale/nl_NL/LC_MESSAGES/django.mo
fleetfinder/locale/nl_NL/LC_MESSAGES/django.po
fleetfinder/locale/pl_PL/LC_MESSAGES/django.mo
fleetfinder/locale/pl_PL/LC_MESSAGES/django.po
fleetfinder/locale/ru/LC_MESSAGES/django.mo
fleetfinder/locale/ru/LC_MESSAGES/django.po
fleetfinder/locale/sk/LC_MESSAGES/django.mo
fleetfinder/locale/sk/LC_MESSAGES/django.po
fleetfinder/locale/uk/LC_MESSAGES/django.mo
fleetfinder/locale/uk/LC_MESSAGES/django.po
fleetfinder/locale/zh_Hans/LC_MESSAGES/django.mo
fleetfinder/locale/zh_Hans/LC_MESSAGES/django.po
fleetfinder/migrations/0001_initial.py
fleetfinder/migrations/0002_esi_error_handling_and_verbose_names.py
fleetfinder/migrations/0003_alter_fleet_fleet_commander_alter_fleet_groups_and_more.py
fleetfinder/migrations/__init__.py
fleetfinder/static/fleetfinder/css/fleetfinder.css
fleetfinder/static/fleetfinder/css/fleetfinder.min.css
fleetfinder/static/fleetfinder/css/fleetfinder.min.css.map
fleetfinder/static/fleetfinder/js/fleetfinder-dashboard.js
fleetfinder/static/fleetfinder/js/fleetfinder-dashboard.min.js
aa_fleetfinder-3.1.1.dist-info/METADATA
aa_fleetfinder-3.1.1.dist-info/WHEEL
aa_fleetfinder-3.1.1.dist-info/licenses/LICENSE
aa_fleetfinder-3.1.1.dist-info/RECORD
